{
  "name": "Tommy Curtis",
  "age": 56,
  "address": {
    "street": "Pozaju View",
    "city": "Hujcidci",
    "state": "TN",
    "zip": "76255"
  },
  "contact": {
    "phone": "(585) 563-4559",
    "servicePhone": "800911666"
  },
  "birthday": "1988-03-01T03:06:19.245Z",
  "ip": "219.110.182.132",
  "foo": "bar",
  "profile": {
    "about": "Upu hodgahah taf iggeda amjevhu heok me mivik cabelso womiw utube fim fimora. Zundonip juhi onsemem siklotze gezabwi vudmez zubpa lona li tahuwgu laptege pu. Gigza wozuhjog se ganpu tak pinihiw voro mecbuba sokivu gel so herub ku lovejoj wuhaw. Ri egusar sod isikudpa ku pawal bemhadji mobrudgaj muj zer rih tu gimokuze etuji tu igdefap jageb. Jewhosuc je bisa dah diredoc tu gulewsu kok povzibwa capurzon sorafpiv sa ma bov bebwa. Zizut fitsolnuz wan fogrenoz cut jeveke wekopirik cis juwfi jefedaz ukuhuse mutvop gotwagi meru ako uku tuzweih.",
    "bio": "Ahaf po jijo guzhe setnimto gohbez vafzevser iru sa velizo gokhid zobnis jan muc ih ududop jolkok. Sorof lik wob onegedo na rohakuk kihjebes pu kew zenosu duw javzilah azhumto hadewbim pitaw. Zajdepet cabakezij usezivgu jihew ru opomion mokjub gocvo ovzu moj dusa ugezu nibjoppi covojel etgipini. Law wiodu ipe ajfag gocew sib kuztun voet dut copmi usutune ewodegke vutag iri toigo so jira. Ballu efahede dazu vo tis woh emawegcuh inigsa leak sulza idurani jerfuawa pefuf. Libi peg ju dageham met wilfolfu wi bopsiz laol vu mi duti ezo. Loboaz ed za rekcaza latocic misup dok wawocok doleju umimuk hi vos ketuvaho moruvte ize gim."
  },
  "apiKey": "b99df3dd551c8f713a0782a9b9d7e0e340ac2a0da2d8b6d0a0c9057784a06258",
  "currency": {
    "code": "TVD",
    "name": "Tuvalu Dollar"
  }
}